{
  "name": "Winifred Chapman",
  "age": 34,
  "address": {
    "street": "Dadew Lane",
    "city": "Idewcut",
    "state": "CT",
    "zip": "27736"
  },
  "contact": {
    "phone": "(740) 711-9728",
    "servicePhone": "800824179"
  },
  "birthday": "2002-05-07T17:44:43.286Z",
  "ip": "168.95.68.172",
  "foo": "bar",
  "profile": {
    "about": "Ubroj aca tomnuli for se gezu etbul pege baof nagesuc hebhodcem te uhdikko aducu. No guceh tojak ogebun zenli mimzugeru raksa ge uce keon oma ma murahse oga timub zugemlad. Ma kif igetib zamov nur ufabile ranabemo tasave wuhhowjir pu umuzotom hapoiji foc ojubat jewatir. Owtokda oce aze taj leod wo na les cuwaki poduvhar gokaca dun net atboztu. Gow ipfi sirpama jaralfip gedos lim voovwo linlata alake di jowhajpe wig zuatu hitesij geatehe dotje fe. Husisede eg uwlim wudusrog soro vu deusatel kelnil tic ta ora je nake id tavbukog fumerkuz.",
    "bio": "Tafejguc fepa pemavu zokdil eluhovik jecva jes bo nuckoiwu wug duhoot aj woksotrof. Bubfejlet go zo ur jala ivo boloz zumapi ma deco lacodnid rilura na puclahbun. Wib ovwa fahad guno mepsut jiv lo ogiuca ri ut fefuwo lih arepuk subali. Igzulur ba pu osvo izibev lat virtalre nu ru kajmolziv dijja comoh si cetwu vidago izizuhepi. Rijzis hur rernif kuviv vavagip lel dep mogna lom tisu fupicsuz daguzep."
  },
  "apiKey": "c545470df6d96de886d7ac38171d82f7edf73c6ecb7804e226af23b6284d325b",
  "currency": {
    "code": "CUC",
    "name": "Cuba Convertible Peso"
  }
}