{
  "name": "Bess Francis",
  "age": 54,
  "address": {
    "street": "Adhe Ridge",
    "city": "Fefbufaz",
    "state": "PA",
    "zip": "83103"
  },
  "contact": {
    "phone": "(472) 718-5345",
    "servicePhone": "800886278"
  },
  "birthday": "1992-10-03T08:39:33.710Z",
  "ip": "199.231.49.248",
  "foo": "bar",
  "profile": {
    "about": "Vemowpor mifsaraf ekose amguk ho nopragtij pavwof ubuwi omuotuf hib leosep for peatdek. Nipe nuz perza kamo fir iv avij rasi mizju velasza keguno muvuliv guzep ca ri wihkik ma fe. Nij voszo rul ligge tu reon piaz zaetepap jof zemcuvoz lemjuz getfokep pubrilkon ti.",
    "bio": "Tuz wukzaw paw omip lalakbun kituega hofo mipunoj teklaja mi picbavza zifje zokazov ig. Widruhde nioledel palot cap isgumoc lolidmo jal ulikarwub nozvolej cuurwes tena wunevcum cado. Tes kicju ik vidaf piceal lowzopdu tiuhe igmawsad rad zunib ropunu ra. Wu wiuk zusiz ozu apkul huse cetjo meg cufip ja tovam we ur emdaweva."
  },
  "apiKey": "03a90c2000763d37ff2cea5ebe04845c358ddfad44a626e468d60759fc27af0f",
  "currency": {
    "code": "SPL",
    "name": "Seborga Luigino"
  }
}