{
  "name": "Marian Hall",
  "age": 50,
  "address": {
    "street": "Ewocus Boulevard",
    "city": "Ehacafkip",
    "state": "NE",
    "zip": "86011"
  },
  "contact": {
    "phone": "(305) 586-8290",
    "servicePhone": "800854548"
  },
  "birthday": "1964-11-14T12:15:04.420Z",
  "ip": "35.20.177.56",
  "foo": "bar",
  "profile": {
    "about": "Suwu zocoke fiwubudu lotha cebca vu velrotjep cadat paltahezo elivided geskag zi lidej. Un wikatdo ujala ugawimab ewewo vobtapsut corikgeg bog ve use aka pa jenwu uwo vozobez uto. Bizjuhipe vomtuhwag pifun domut wulom fe fimih merhajav ih iki hogokvu pobnamen babammob.",
    "bio": "Ezse akuru cizlihi noflujo epepeku fir teduwjev rat deme aje vabvasi teluk fatzi aka kiir vuguk zipup ga. Koldiwi jodisos jemliv zufgek zol fevkic pu pamo vaeti rungalpa cofi wegjob. Civam ugrajha at nas okajeot usiugo zasohar zupusep ulaka ugeb igacofi mezjok kelur. Kalozoh habanhar enva ramhat oharegun figga mazmifar wuru acicup kaza juebbeb uloar non fiwive kucefpid zeur meforut werpu. Aprej jegbirga uziru odibi az tag subo gunvej ape irrij go bujbew reni. Azzupe hufvehmuh sunlaza bitnunbu hisi watub rer fetnod atiz uswel popive rutjip."
  },
  "apiKey": "be7e983134583c42faf36fcb792543556349aa901395948c0b580b4022b9c848",
  "currency": {
    "code": "LKR",
    "name": "Sri Lanka Rupee"
  }
}